{
  "headings": {
    "family": "Segoe UI",
    "fallback": "system-ui, -apple-system, sans-serif",
    "weight": "600"
  },
  "body": {
    "family": "Segoe UI",
    "fallback": "system-ui, -apple-system, sans-serif",
    "weight": "400"
  },
  "mono": {
    "family": "Cascadia Code",
    "fallback": "Consolas, monospace",
    "weight": "400"
  },
  "source": "system",
  "_meta": {
    "rationale": "System fonts for a desktop-first tool — zero load time, native feel. Segoe UI is Windows 11 default, Cascadia Code ships with Windows Terminal. For web (landing page), swap to Inter (headings/body) and JetBrains Mono (code) via Google Fonts."
  }
}
